loguniform/LogUniform.py
loguniform/__init__.py
LogUniform-2.0.0.dist-info/LICENSE
LogUniform-2.0.0.dist-info/METADATA
LogUniform-2.0.0.dist-info/WHEEL
LogUniform-2.0.0.dist-info/top_level.txt
LogUniform-2.0.0.dist-info/RECORD
